dfdrift/__init__.py
dfdrift/alerters.py
dfdrift/pandas.py
dfdrift/storages.py
dfdrift/validator.py
dfdrift-0.5.0.dist-info/METADATA
dfdrift-0.5.0.dist-info/WHEEL
dfdrift-0.5.0.dist-info/top_level.txt
dfdrift-0.5.0.dist-info/RECORD
