Metadata-Version: 2.4
Name: dfdrift
Version: 0.5.0
Summary: DataFrame schema drift detection and alerting
Author-email: Keisuke Ogaki <ogaki@example.com>
License-Expression: MIT
Project-URL: Homepage, https://github.com/Hi-king/dfdrift
Project-URL: Repository, https://github.com/Hi-king/dfdrift
Project-URL: Issues, https://github.com/Hi-king/dfdrift/issues
Keywords: pandas,dataframe,schema,drift,validation,monitoring
Classifier: Development Status :: 3 - Alpha
Classifier: Intended Audience :: Developers
Classifier: Programming Language :: Python :: 3
Classifier: Programming Language :: Python :: 3.9
Classifier: Programming Language :: Python :: 3.10
Classifier: Programming Language :: Python :: 3.11
Classifier: Programming Language :: Python :: 3.12
Classifier: Topic :: Software Development :: Libraries :: Python Modules
Classifier: Topic :: Scientific/Engineering :: Information Analysis
Requires-Python: <3.13,>=3.9
Requires-Dist: pandas>=1.5.0
Provides-Extra: test
Requires-Dist: pytest>=7.0; extra == "test"
Requires-Dist: pytest-cov>=4.0; extra == "test"
Requires-Dist: tox>=4.0; extra == "test"
Provides-Extra: slack
Requires-Dist: slack-sdk>=3.19.0; extra == "slack"
Provides-Extra: gcs
Requires-Dist: google-cloud-storage>=2.18.0; extra == "gcs"
